{
  "main": {
    "id": "71201566fb8269e6",
    "type": "split",
    "children": [
      {
        "id": "ee5c2be903d00b94",
        "type": "tabs",
        "children": [
          {
            "id": "f00a56095fe2ad2a",
            "type": "leaf",
            "state": {
              "type": "markdown",
              "state": {
                "file": "Gameplay Ideas/Chapter 1 - Layout.md",
                "mode": "source",
                "source": false
              }
            }
          },
          {
            "id": "1826e64aaf8cbe6f",
            "type": "leaf",
            "state": {
              "type": "markdown",
              "state": {
                "file": "Lore/What happens at the end of the game.md",
                "mode": "source",
                "source": false
              }
            }
          },
          {
            "id": "23e49ed614850374",
            "type": "leaf",
            "state": {
              "type": "markdown",
              "state": {
                "file": "Logs/Mission Monkey Update 0.4 Log 3.md",
                "mode": "source",
                "source": false
              }
            }
          }
        ],
        "currentTab": 2
      }
    ],
    "direction": "vertical"
  },
  "left": {
    "id": "b962d58f20e38aba",
    "type": "split",
    "children": [
      {
        "id": "364e2e4dbfed05bb",
        "type": "tabs",
        "children": [
          {
            "id": "ed61629f19f3c13d",
            "type": "leaf",
            "state": {
              "type": "file-explorer",
              "state": {
                "sortOrder": "alphabetical"
              }
            }
          },
          {
            "id": "66cee894cd42c924",
            "type": "leaf",
            "state": {
              "type": "search",
              "state": {
                "query": "",
                "matchingCase": false,
                "explainSearch": false,
                "collapseAll": false,
                "extraContext": false,
                "sortOrder": "alphabetical"
              }
            }
          },
          {
            "id": "cb26a592f540ef7e",
            "type": "leaf",
            "state": {
              "type": "bookmarks",
              "state": {}
            }
          }
        ]
      }
    ],
    "direction": "horizontal",
    "width": 300
  },
  "right": {
    "id": "795bc151e73f7ebf",
    "type": "split",
    "children": [
      {
        "id": "96c3076e7797511e",
        "type": "tabs",
        "children": [
          {
            "id": "62b3bd530dabf6f7",
            "type": "leaf",
            "state": {
              "type": "backlink",
              "state": {
                "file": "Logs/Mission Monkey Update 0.4 Log 3.md",
                "collapseAll": false,
                "extraContext": false,
                "sortOrder": "alphabetical",
                "showSearch": false,
                "searchQuery": "",
                "backlinkCollapsed": false,
                "unlinkedCollapsed": true
              }
            }
          },
          {
            "id": "cd21364e68e06d21",
            "type": "leaf",
            "state": {
              "type": "outgoing-link",
              "state": {
                "file": "Logs/Mission Monkey Update 0.4 Log 3.md",
                "linksCollapsed": false,
                "unlinkedCollapsed": true
              }
            }
          },
          {
            "id": "3fc644744c73da9a",
            "type": "leaf",
            "state": {
              "type": "tag",
              "state": {
                "sortOrder": "frequency",
                "useHierarchy": true
              }
            }
          },
          {
            "id": "81ddbb444ee2b72d",
            "type": "leaf",
            "state": {
              "type": "outline",
              "state": {
                "file": "Logs/Mission Monkey Update 0.4 Log 3.md"
              }
            }
          }
        ]
      }
    ],
    "direction": "horizontal",
    "width": 300,
    "collapsed": true
  },
  "left-ribbon": {
    "hiddenItems": {
      "switcher:Open quick switcher": false,
      "graph:Open graph view": false,
      "canvas:Create new canvas": false,
      "daily-notes:Open today's daily note": false,
      "templates:Insert template": false,
      "command-palette:Open command palette": false
    }
  },
  "active": "23e49ed614850374",
  "lastOpenFiles": [
    "Pasted image 20240224011956.png",
    "Pasted image 20240224011543.png",
    "Pasted image 20240224011528.png",
    "The Hub Hub.md",
    "Lore/What happens at the end of the game.md",
    "Gameplay Ideas/Chapter 1 - Layout.md",
    "Gameplay Ideas/Chapter 1 - Microgravity.md",
    "Logs/Mission Monkey Update 0.4 Log 3.md",
    "Logs/Mission Monkey Update 0.4 Log 2.md",
    "2024-02-18 10-38-04.mp4",
    "Pasted image 20240218110719.png",
    "Notes/How The Enemy AI System Will Be Designed.md",
    "Lore/Basic Lore & Story Overview.md",
    "Lore/The story behind the anti-company org.md",
    "Lore/How The Company Got So Big.md",
    "Logs/Log 2.5.md",
    "Gameplay ideas hub page.md",
    "README.md",
    "example file.md",
    "Gameplay Ideas/Enemy Type - Invisible.md",
    "Gameplay Ideas/Gameplay Systems",
    "Gameplay Ideas/Gameplay on chapters that involve gas giants.md",
    "Gameplay Ideas/How interactions can be handled in 0.4.md",
    "Gameplay Ideas/What type of game is Mission Monkey anyways.md",
    "The Notes Hub Page.md",
    "Gameplay Ideas/Chapter 1 - Final Boss.md",
    "Gameplay Ideas/Chapter Order.md",
    "Gameplay Ideas/Use of the moon in the game.md",
    "Logs/Mission Monkey Update 0.4 Log 1.md",
    "The Lore Hub Page.md",
    "Lore/How the company grew to have such massive power.md",
    "Lore",
    "Screenshots/ObjectiveUI.png",
    "Screenshots/PlayerUI.png",
    "Screenshots/DeathUI.png",
    "Screenshots/HealthBar.gif",
    "Screenshots/LoadSaveMenu.png",
    "Screenshots/OptionsMenu.png",
    "Screenshots/UpdateMenu.png",
    "Notes",
    "Screenshots",
    "Gameplay Ideas",
    "Logs"
  ]
}